README.md
setup.py
scrapy_bloomerfiler/_version.py
scrapy_bloomerfiler/bloomfilerpipeline.py
scrapy_bloomerfiler/spiders.py
scrapy_bloomerfiler.egg-info/PKG-INFO
scrapy_bloomerfiler.egg-info/SOURCES.txt
scrapy_bloomerfiler.egg-info/dependency_links.txt
scrapy_bloomerfiler.egg-info/requires.txt
scrapy_bloomerfiler.egg-info/top_level.txt