Metadata-Version: 2.1
Name: scrapy-bloomerfiler
Version: 0.1.2
Summary: 新增 scrapy pipeline 对 item 目标字段组合除重
Author: buliqioqiolibusdo
Author-email: xinchacha@xcc.com
